odoo/addons/utm_medium_multi_company/README.rst
odoo/addons/utm_medium_multi_company/__init__.py
odoo/addons/utm_medium_multi_company/__manifest__.py
odoo/addons/utm_medium_multi_company/i18n/utm_medium_multi_company.pot
odoo/addons/utm_medium_multi_company/models/__init__.py
odoo/addons/utm_medium_multi_company/models/utm_medium.py
odoo/addons/utm_medium_multi_company/readme/CONTRIBUTORS.rst
odoo/addons/utm_medium_multi_company/readme/DESCRIPTION.rst
odoo/addons/utm_medium_multi_company/security/utm_medium.xml
odoo/addons/utm_medium_multi_company/static/description/icon.png
odoo/addons/utm_medium_multi_company/static/description/index.html
odoo/addons/utm_medium_multi_company/views/utm_medium.xml
odoo12_addon_utm_medium_multi_company-12.0.1.0.0.99.dev4.dist-info/METADATA
odoo12_addon_utm_medium_multi_company-12.0.1.0.0.99.dev4.dist-info/WHEEL
odoo12_addon_utm_medium_multi_company-12.0.1.0.0.99.dev4.dist-info/top_level.txt
odoo12_addon_utm_medium_multi_company-12.0.1.0.0.99.dev4.dist-info/RECORD
